kwargify_cli/__init__.py
kwargify_cli/cli.py
kwargify_cli-0.1.1.dist-info/METADATA
kwargify_cli-0.1.1.dist-info/WHEEL
kwargify_cli-0.1.1.dist-info/entry_points.txt
kwargify_cli-0.1.1.dist-info/RECORD
