Metadata-Version: 2.3
Name: kwargify-cli
Version: 0.1.1
Summary: A CLI to help build AI Agents or AI Workflows with the same DX as dbt.
License: MIT
Author: lalit.gehani
Author-email: lalit.gehani@yahoo.co.in
Requires-Python: >=3.12
Classifier: License :: OSI Approved :: MIT License
Classifier: Programming Language :: Python :: 3
Classifier: Programming Language :: Python :: 3.12
Classifier: Programming Language :: Python :: 3.13
